BulkPayment/BulkPayment.py
BulkPayment/BulkPaymentPayload.py
BulkPayment/__init__.py
GetAccountEnquiry/AccountEnquiry.py
GetAccountEnquiry/AccountEnquiryPayload.py
GetAccountEnquiry/__init__.py
GetActiveBanks/GetActiveBanks.py
GetActiveBanks/GetActiveBanksPayload.py
GetActiveBanks/__init__.py
GetAddAccount/AddAccount.py
GetAddAccount/AddAccountPayload.py
GetAddAccount/__init__.py
PaymentStatus/PaymentStatus.py
PaymentStatus/PaymentStatusPayload.py
PaymentStatus/__init__.py
PaymentStatusBulk/PaymentStatusBulk.py
PaymentStatusBulk/PaymentStatusBulkPayload.py
PaymentStatusBulk/__init__.py
RemitaInterbankService/BaseResponse.py
RemitaInterbankService/Credentials.py
RemitaInterbankService/EncryptionUtil.py
RemitaInterbankService/EnvironmentConfig.py
RemitaInterbankService/RemitaRITs.py
RemitaInterbankService/SdkResponseCode.py
RemitaInterbankService/Timestamp.py
RemitaInterbankService/__init__.py
SinglePayment/SinglePayment.py
SinglePayment/SinglePaymentPayload.py
SinglePayment/__init__.py
ValidateAccountOTP/ValidateAccountOTP.py
ValidateAccountOTP/ValidateAccountOTPPayload.py
ValidateAccountOTP/__init__.py
remita_rits-1.0.6.dist-info/METADATA
remita_rits-1.0.6.dist-info/WHEEL
remita_rits-1.0.6.dist-info/top_level.txt
remita_rits-1.0.6.dist-info/RECORD
