Metadata-Version: 2.1
Name: remita-rits
Version: 1.0.6
Summary: Python SDK for Remita Interbank Transfer Service simple APIs
Home-page: https://github.com/RemitaNet/rits-sdk-python
Author: SystemSpecs Limited
Author-email: ipgtechnologyteam@gmail.com
License: UNKNOWN
Platform: UNKNOWN
Classifier: Programming Language :: Python :: 3
Classifier: License :: OSI Approved :: MIT License
Classifier: Operating System :: OS Independent
Requires-Python: >=3.4
